shylock/__init__.py
shylock/aio/lock.py
shylock/backends/__init__.py
shylock/backends/aioarangodb.py
shylock/backends/motorasyncio.py
shylock/backends/pymongo.py
shylock/backends/pythonarango.py
shylock/backends/tests/test_motorasyncio.py
shylock/exceptions.py
shylock/lock.py
shylock/manager.py
shylock-1.2.1.dist-info/METADATA
shylock-1.2.1.dist-info/WHEEL
shylock-1.2.1.dist-info/LICENSE
shylock-1.2.1.dist-info/RECORD
