Metadata-Version: 2.1
Name: shylock
Version: 1.2.1
Summary: Distributed locks in Python, similar to https://github.com/vaidik/sherlock - also with asyncio support
Home-page: https://github.com/lietu/shylock/
License: BSD-3-Clause
Keywords: distributed,locking,lock,asyncio
Author: Janne Enberg
Author-email: janne.enberg@lietu.net
Requires-Python: >=3.7,<4.0
Classifier: License :: OSI Approved :: BSD License
Classifier: Programming Language :: Python :: 3
Classifier: Programming Language :: Python :: 3.7
Classifier: Programming Language :: Python :: 3.8
Classifier: Programming Language :: Python :: 3.9
Classifier: Programming Language :: Python :: 3.10
Classifier: Programming Language :: Python :: 3.11
Provides-Extra: aioarangodb
Provides-Extra: motor
Provides-Extra: pymongo
Provides-Extra: python-arango
Requires-Dist: aioarangodb (>=0.1.2,<0.2.0) ; extra == "aioarangodb"
Requires-Dist: motor (>=3.0.0,<4.0.0) ; extra == "motor"
Requires-Dist: pymongo (>=4.1,<5.0) ; extra == "pymongo"
Requires-Dist: python-arango (>=5.4.0,<6.0.0) ; extra == "python-arango"
Project-URL: Documentation, https://github.com/lietu/shylock/
Project-URL: Repository, https://github.com/lietu/shylock/
